{
  "F3_K11_8F_3390": {
    "done": true
  },
  "F3_K11_8F_3260": {
    "done": false
  },
  "F3_K11_8F_3670": {
    "done": false
  },
  "F3_K11_5F_3260": {
    "done": false
  },
  "F3_K11_6F_3390": {
    "done": false
  },
  "F3_K11_9F_3260": {
    "done": false
  },
  "F3_K11_10F_3390": {
    "done": false
  },
  "F3_K11_11F_3260": {
    "done": false
  },
  "F3_K11_18F_3390": {
    "done": false
  },
  "F3_K11_12F_3260": {
    "done": false
  },
  "F3_K11_13F_3390": {
    "done": false
  },
  "F3_K11_19F_3260": {
    "done": false
  }
}